Workbook
Name _Toc94971774: 機能概要・画面遷移図!#REF!
Name _Toc94971775: 機能概要・画面遷移図!#REF!

Sheet タイトル
G11: =I40 -> 学生勤務管理システム
G14: =I44 -> CZ-010_雇用情報マスタ
G17: =I42
G20: =I51 -> 【 Ver 1.12 】
J27: =TEXT(I47,"yyyy年")&IF(LEFT(TEXT(I47,"mm"),1)="0"," ","")&TEXT(I47,"m月")&IF(LEFT(TEXT(I47,"dd"),1)="0"," ","")&TEXT(I47,"d日")&"作成" -> 2023年 9月27日作成
J29: =IF(I49=" ※ページ毎に個別入力"," 年 月 日改訂",TEXT(I49,"yyyy年")&IF(LEFT(TEXT(I49,"mm"),1)="0"," ","")&TEXT(I49,"m月")&IF(LEFT(TEXT(I49,"dd"),1)="0"," ","")&TEXT(I49,"d日")&"改訂") -> 2025年 6月12日改訂
B38: 見出し部タイトル制御テーブル
B39: タイトル項目 | I39: タイトル項目埋め込み内容
B40: ①システム名 | I40: 学生勤務管理システム
B41: ②サブシステム名 | I41: 共通機能
B42: ③分類名
B43: ④作業工程名 | I43: 機能設計
B44: ⑤ドキュメント代表名 | I44: CZ-010_雇用情報マスタ
B45: ⑥ドキュメント詳細名 | I45: ※ページ毎に個別入力
B46: ⑦作成者 | I46: 木田 優
B47: ⑧作成日 | I47: 45196
B48: ⑦改定者 | I48: ※ページ毎に個別入力
B49: ⑧改定日 | I49: =TEXT(MAX(改訂履歴!J5:J992),"yyyy/mm/dd") -> 2025/06/12
B50: ⑨管理記号 | I50: DUC010
B51: ⑩Ｖｅｒ | I51: ="【 Ver " & TEXT(MAX(改訂履歴!E5:E992),"0.00") & " 】" -> 【 Ver 1.12 】

Sheet 改訂履歴
A1: 改訂履歴
A3: No | E3: Ver | J3: 新規／改訂日 | R3: 区分 | W3: 改訂箇所 | AH3: 改訂理由 | BR3: 新規／改訂者
W4: 頁 | AA4: 機能
A5: 1 | E5: 1 | J5: =タイトル!I47 -> 45196 | R5: 新規 | AH5: 新規作成 | BR5: 木田 優
A6: 2 | E6: 1.01 | J6: 45209 | R6: 変更 | AA6: 雇用情報マスタ | AH6: 人事給与連携データフォーマットを全職種共通仕様に変更 | BR6: 木田 優
A7: 3 | E7: 1.02 | J7: 45216 | R7: 変更 | AA7: 雇用情報マスタ | AH7: 検索条件に開講年度を雇用年度に変更 検索条件に更新日を追加 一覧から身分と複数身分IDを削除 | BR7: 木田 優
A8: 4 | J8: 45216 | R8: 変更 | AA8: 雇用情報マスタ編集 | AH8: 雇用年度の位置を変更し、開講年度を削除 身分を削除 業務、予算、配分先コードをリストボックスに変更 | BR8: 木田 優
A9: 5 | J9: 45216 | R9: 変更 | AA9: 雇用情報マスタ取込 | AH9: 雇用情報データフォーマットを編集項目に合わせて修正 | BR9: 木田 優
A10: 6 | J10: 45223 | R10: 変更 | AA10: 雇用情報マスタ取込 | AH10: 複数身分IDの採番ルールを追記 | BR10: 木田 優
A11: 7 | E11: 1.03 | J11: 45238 | R11: 変更 | AA11: 雇用情報マスタ | AH11: 検索条件の必須条件を追加 一覧に雇用情報を表示 人事給与連携データフォーマットの組織コードの設定内容を変更 | BR11: 木田 優
A12: 8 | J12: 45238 | R12: 変更 | AA12: 雇用情報マスタ編集 | AH12: 職種が一般の場合、業務内容等を必須にする 業務・予算・配分先コードと雇用部課の紐付き説明を追記 | BR12: 木田 優
A13: 9 | J13: 45238 | R13: 変更 | AA13: 雇用情報マスタ取込 | AH13: 雇用情報フォーマットに必須項目列を追加し、補足説明を追記 | BR13: 木田 優
A14: 10 | J14: 45238 | R14: 変更 | AA14: 雇用情報マスタ編集 | AH14: 雇用年度のリストボックスの取得仕様を変更 | BR14: 木田 優
A15: 11 | J15: 45267 | R15: 変更 | AA15: 雇用情報マスタ | AH15: インタフェース定義資料変更に基づくフォーマット内容の変更反映 | BR15: 木田 優
A16: 12 | E16: 1.04 | J16: 45274 | R16: 変更 | AA16: 雇用情報マスタ編集 | AH16: 業務、予算、配分先のリストボックスの抽出キーを雇用部課から部署連番に変更 登録、更新時に過去年度の登録はエラー | BR16: 木田 優
A17: 13 | E17: 1.05 | J17: 45278 | R17: 変更 | AA17: 雇用情報マスタ編集 | AH17: 雇用開始日、終了日を学年暦から取得する際の方法を明記 | BR17: 中村 恒太郎
A18: 14 | J18: 45278 | R18: 変更 | AA18: 雇用情報マスタ編集 | AH18: 一般（学生アルバイト）の複数身分IDの採番方法を見直し。 | BR18: 中村 恒太郎
A19: 15 | J19: 45278 | R19: 変更 | AA19: 雇用情報マスタ | AH19: に情報ダウンロードフォーマット作成日時、最終更新者、処理ＩＤ、更新日時を追加。 | BR19: 中村 恒太郎
A20: 16 | E20: 1.06 | J20: 45314 | R20: 変更 | AA20: 雇用情報マスタ | AH20: 検索条件の削減 | BR20: 木田 優
A21: 17 | J21: 45314 | R21: 変更 | AA21: 雇用情報マスタ編集 | AH21: 複数身分IDの採番ルールを変更 | BR21: 木田 優
A22: 18 | E22: 1.07 | J22: 45454 | R22: 変更 | AA22: 雇用情報マスタ | AH22: ダウンロードファイル名の変更 （2024年度保守_項番24） | BR22: 木田 優
A23: 19 | E23: 1.08 | J23: 45639 | R23: 変更 | AA23: 雇用情報マスタ編集 雇用情報マスタ取込 | AH23: TA/SAの時の教員リストボックスを廃止し、テキストボックスに変更 （2024年度改修_項番2） | BR23: 木田 優
A24: 20 | E24: 1.09 | J24: 45639 | R24: 変更 | AA24: 雇用情報マスタ | AH24: 人事給与連携データフォーマット任意項目コード1に配分先をセットする （2024年度改修_項番3） | BR24: 木田 優
A25: 21 | E25: 1.1 | J25: 45642 | R25: 変更 | AA25: 雇用情報マスタ編集 雇用情報マスタ取込 | AH25: 管理者権限では雇用部課と業務・予算コードの制御を除いて登録できるようにする （2024年度改修_項番4） | BR25: 木田 優
A26: 22 | E26: 1.11 | J26: 45706 | R26: 変更 | AA26: 雇用情報マスタ取込 | AH26: 雇用情報取込時に雇用年度の存在チェックを追加 （2024年度改修_保守３） | BR26: 木田 優
A27: 23 | E27: 1.12 | J27: 45820 | R27: 変更 | AA27: 雇用情報マスタ | AH27: 単価一覧の処理年・月は無条件にNULLを出力する （2025年度改修_項番18） | BR27: 木田 優

Sheet 機能概要・画面遷移図
A1: システム名 | I1: =タイトル!I40 -> 学生勤務管理システム | AE1: 工 程 | AL1: =タイトル!I43 -> 機能設計 | BI1: 作 成 | BM1: =タイトル!I46 -> 木田 優 | BW1: =タイトル!I47 -> 45196 | CF1: 管理記号 | CK1: =タイトル!I50 -> DUC010
A2: サブシステム名 | I2: =タイトル!I41 -> 共通機能 | AE2: ドキュメント | AL2: =タイトル!I44 -> CZ-010_雇用情報マスタ | BI2: 改 訂
A4: 機能名称 | I4: =" " & RIGHT(タイトル!I44,LEN(タイトル!I44)-8) -> 雇用情報マスタ | AL4: 機能ＩＤ | AS4: =LEFT(タイトル!I44,7) -> CZ-010 | BI4: 利用想定ユーザー | BT4: 管理者・担当者
A5: 機 能 概 要
B7: 雇用情報を登録・編集・照会する時に使用する。
B8: EXCELを取り込み、雇用情報の一括登録（更新）をする時に使用する。
A10: 画 面 遷 移 図
C13: ○ホーム画面 | AH13: ○雇用情報マスタ画面 | BK13: ○雇用情報マスタ編集画面
D14: （CC-020-01G） | AI14: （CZ-010-01G） | BA14: 選択ボタン | BL14: （CZ-010-02G）
V15: 雇用情報マスタボタン | BA15: or
BA16: 新規作成ボタン
BA20: 戻るボタン
P25: 人事給与連携データ作成ボタン | AK25: 雇用情報ダウンロード
Q26: （CZ-010-03C） | AK26: ボタン | BC26: 雇用情報取込ボタン
AH27: （CZ-010-06E） | AS27: 戻るボタン
AV29: ○雇用情報マスタ取込画面
AW30: （CZ-010-04G）

Sheet 雇用情報マスタ
A1: システム名 | I1: =タイトル!I40 -> 学生勤務管理システム | AE1: 工 程 | AL1: 機能設計 | BI1: 作 成 | BM1: =タイトル!I46 -> 木田 優 | BW1: =タイトル!I47 -> 45196 | CF1: 管理記号 | CK1: =タイトル!I50 -> DUC010
A2: サブシステム名 | I2: 共通機能 | AE2: ドキュメント | AL2: =タイトル!I44 -> CZ-010_雇用情報マスタ | BI2: 改 訂 | BM2: 木田 優 | BW2: 45820
A4: 画面名称 | I4: =" " & RIGHT(CELL("filename",A1),LEN(CELL("filename",A1))-FIND("]",CELL("filename",A1))) -> 雇用情報マスタ | AL4: 画面ＩＤ | AS4: CZ-010-01G | BI4: 利用想定ユーザー | BT4: 管理者、担当者
A5: 画面レイアウト | BI5: 機能概要
BJ7: ・ | BK7: 雇用情報を登録・照会・編集する時に使用する。
BJ8: ・ | BK8: 雇用マスタ取込画面への遷移機能がある。
BJ9: ・ | BK9: 照会した結果を人事給与連携データとしてＣＳＶ出力することができる。
BJ10: ・ | BK10: EXCELを取り込み、雇用情報の一括登録（更新）をする時に使用する。
BI12: 画面説明 （処理内容・アクション等）
BJ14: ・ | BK14: 雇用年度はシステム日付に該当する年度を初期表示する。
BJ15: ・ | BK15: 更新日のカレンダーを押下すると、カレンダーを表示する。
BJ17: ・ | BK17: 雇用年度、学生ID、学生氏名、雇用部課
BK18: のいづれかが検索条件にないとエラーとする。
BJ20: ・ | BK20: 検索ボタンを押下すると、入力された検索条件を基に該当する雇用情報を
BK21: 表示する。
BJ22: ・ | BK22: 検索結果の行は30行を最大とし、31行目以降はページング機能を使用して
BK23: 表示する行を切り替える。
BJ25: ・ | BK25: 選択ボタンを押下すると、雇用情報マスタ編集画面を表示する。
BJ27: ・ | BK27: 新規作成ボタンを押下すると、雇用情報マスタ編集画面を表示する。
BJ29: ・ | BK29: 雇用情報ダウンロードボタンを押下すると、画面に表示されている全結果を
BK30: ＥＸＣＥＬダウンロードする。
BJ32: ・ | BK32: 雇用情報取込ボタンを押下すると、雇用情報マスタ取込画面を表示する。
BJ34: ・ | BK34: 人事給与連携データ作成ボタンを押下すると、画面に表示されている
BK35: 全結果をＣＳＶ出力する。
BK36: 又、併せて複数身分ＩＤごとの単価一覧をＥＸＣＥＬ出力する。
A38: リストボックス | BI38: 権限による画面制御
A39: 項目名 | K39: 内容 | AW39: 並び順
A40: 雇用年度 | K40: 雇用情報マスタの雇用年度をグループ化して表示 | AW40: 雇用年度の降順 | BJ40: 権限が担当者の場合は、人事給与連携データ作成ボタンは非表示にする。
A41: 職種 | K41: 職種 | AW41: 昇順
A42: 雇用部課 | K42: 雇用部課 | AW42: 昇順
BI43: 一覧の並び順
BJ45: 雇用年度（昇順）→学生ID（昇順）→雇用情報ID（昇順）
A48: 画 面 補 足 説 明
B50: ○入力項目（検索条件） | AY50: ○リストボックス（続き）
B51: 項目名 | P51: 入力必須 | U51: 桁数 | X51: 入力制限等 | AZ51: 【雇用部課】
B52: 雇用年度 | P52: △ | U52: - | X52: リストボックス | BA52: 雇用部課 | BW52: ▼
B53: 学生ID | P53: △ | U53: 11 | X53: 半角数字、前方一致検索 | BH53: 101：法人事務室
B54: 学生氏名 | P54: △ | U54: 100 | X54: 前方一致検索 | BH54: 102：監査室
B55: 職種 | P55: × | U55: - | X55: リストボックス | BH55: 103：募金課
B56: 雇用部課 | P56: △ | U56: 3 | BH56: 104：150周年記念事務室
B57: 更新日 | J57: 開始年月日 | P57: × | U57: - | X57: 西暦日付 開始年月日と終了年月日の両方が入力された場合、開始年月日＞終了年月日であればエラーにする。 ※カレンダーを押下するとカレンダー画面が別ウィンドウで表示される。 | BH57: ・
BH58: ・
BH59: ・
J60: 終了年月日 | P60: × | U60: -
AY61: ○雇用情報の表示内容
AZ62: ※職種によって表示が異なります。
B63: 必須：△ | F63: （どれか一つでも検索条件にないとエラーとする） | BA63: 職種 | BJ63: 項目１ | BQ63: 項目２ | BX63: 項目３ | CE63: 項目４
BA64: TA | BJ64: 職種名 | BQ64: 曜日講時※1 | BX64: 科目・クラス | CE64: 担当教員（姓）
B65: ○出力項目 | BA65: SA | BJ65: 職種名 | BQ65: 曜日講時※1 | BX65: 科目・クラス | CE65: 担当教員（姓）
B66: 項目名 | K66: 編集内容等 | BA66: RA | BJ66: 職種名 | BQ66: 担当教員（姓）
B67: 雇用年度 | K67: yyyy | BA67: LA | BJ67: 職種名 | BQ67: 雇用部課名称
B68: 学生ID | BA68: 留学生チューター | BJ68: 職種名 | BQ68: 担当教員（姓）
B69: 学生名 | BA69: 研究活動等支援員 | BJ69: 職種名 | BQ69: 担当教員（姓）
B70: 雇用情報 | BA70: 一般 | BJ70: 職種名 | BQ70: 雇用部課名称 | BX70: 業務内容等
BA71: ※1 曜日講時が複数存在する場合は（、）で区切り1行で表示する
B72: ○リストボックス
C73: 【雇用年度】 | W73: 【職種】 | AY73: ○エラーメッセージ
D74: 雇用年度 | T74: ▼ | X74: 職種 | AS74: ▼ | AZ74: エラー条件 | BU74: エラーメッセージ
L75: 2023 | AF75: TA | AZ75: 雇用年度・学生ID・学生氏名・雇用部課のいづれかが未入力の場合 | BU75: 検索条件が不足しています。検索条件の指定を追加してください。
L76: 2022 | AF76: SA
L77: 2021 | AF77: RA
AF78: LA
AF79: 留学生チューター
AF80: 研究活動等支援員
AF81: 一般
A91: 画 面 補 足 説 明
B93: 〇単価一覧フォーマット | O93: ファイル名：『単価一覧_[ユーザID]_yyyymmdd.csv』 | AZ93: 〇校地間移動単価一覧フォーマット | BQ93: ファイル名：『校地間移動単価一覧_[ユーザID]_yyyymmdd.csv』
C94: 項目名 | Q94: 備考 | BA94: 項目名 | BO94: 備考
C95: 法人コード | Q95: 10000 固定 | BA95: 法人コード | BO95: 10000 固定
C96: 処理年 | Q96: 雇用開始日～終了と出力する日によって、設定値が変動する。 空白 固定 | BA96: 処理年 | BO96: 単価一覧フォーマットと同じ | CT96: 2025年度改修_項番18
BA97: 処理月 | BO97: 単価一覧フォーマットと同じ
C98: 処理月 | Q98: 雇用開始日～終了と出力する日によって、設定値が変動する。 空白 固定 | BA98: 処理回数 | BO98: 0 固定 | CT98: 2025年度改修_項番18
BA99: 処理区分 | BO99: 1 固定
C100: 処理回数 | Q100: 0 固定 | BA100: 職員番号
C101: 処理区分 | Q101: 1 固定 | BA101: 複数身分識別ＩＤ
C102: 職員番号 | BA102: 項目ＩＤ | BO102: H560201 固定
C103: 複数身分識別ＩＤ | BA103: 金額 | BO103: ユーザコードマスタ[UC001].職種マスタ.校地移動単価
C104: 項目ＩＤ | Q104: H012100 固定 | BA104: 終了処理年 | BO104: 空白 固定
C105: 金額 | Q105: 個別単価、個別単価が無ければ職種毎の標準単価 | BA105: 終了処理月 | BO105: 空白 固定
C106: 終了処理年 | Q106: 空白 固定 | BA106: 終了処理回数 | BO106: 空白 固定
C107: 終了処理月 | Q107: 空白 固定
C108: 終了処理回数 | Q108: 空白 固定 | AZ108: ○雇用情報ダウンロードフォーマット | BS108: ファイル名：『雇用情報_[ユーザID]_yyyymmdd.xlsx』
BA109: 項目名 | BO109: 備考
BA110: 雇用情報通番
BA111: 雇用年度
BA112: 社員番号 | BO112: 利用者の場合は学生ＩＤ
BA113: 職種 | BO113: 1：ＴＡ、2：ＳＡ、3：ＲＡ、4：ＬＡ・・・・・
BA114: 雇用部課コード | BO114: 101：法人事務室、102：監査室、103：募金課・・・・
BA115: 予算区分 | BO115: 00：－、01：TA 学部、02：TA 大学院 ・・・・・
BA116: 科目コード
BA117: クラスコード
BA118: 科目名
BA119: 主担当教員コード
BA120: 雇用開始日
BA121: 雇用終了日
BA122: 業務コード
BA123: 予算コード
BA124: 配分先コード
BA125: 業務内容等
BA126: 複数身分ＩＤ
...

Sheet 雇用情報マスタ編集
A1: システム名 | I1: =タイトル!I40 -> 学生勤務管理システム | AE1: 工 程 | AL1: 機能設計 | BI1: 作 成 | BM1: =タイトル!I46 -> 木田 優 | BW1: =タイトル!I47 -> 45196 | CF1: 管理記号 | CK1: =タイトル!I50 -> DUC010
A2: サブシステム名 | I2: 共通機能 | AE2: ドキュメント | AL2: =タイトル!I44 -> CZ-010_雇用情報マスタ | BI2: 改 訂 | BM2: 木田 優 | BW2: 45642
A4: 画面名称 | I4: =" " & RIGHT(CELL("filename",A1),LEN(CELL("filename",A1))-FIND("]",CELL("filename",A1))) -> 雇用情報マスタ編集 | AL4: 画面ＩＤ | AS4: CZ-010-02G | BI4: 利用想定ユーザー | BT4: 管理者、担当者
A5: 画面レイアウト | BI5: 機能概要
BJ7: ・ | BK7: 雇用情報を登録・編集・削除する時に使用する。
BI12: 画面説明 （処理内容・アクション等）
BJ14: ・ | BK14: 学生検索ボタンを押下すると、社員選択ポップアップを表示する。
BJ16: ・ | BK16: 科目検索ボタンを押下すると、科目選択ポップアップを表示する。
BJ18: ・ | BK18: 雇用開始日、雇用終了日のカレンダーを押下すると、
BK19: カレンダーを表示する。
BJ21: ・ | BK21: 職種によって、必須項目が変動する。
BK22: ※画面補足説明参照
BJ24: ・ | BK24: 登録、更新時に雇用年度がシステム日付の年度より過去年度の場合は、
BK25: 登録、更新できないようにエラーを表示する。
BK26: 「システム日付年度より過去の年度は登録できません。」
A38: リストボックス | BI38: 権限による画面制御
A39: 項目名 | K39: 内容 | AW39: 並び順
A40: 雇用年度 | K40: 給与支給日マスタの雇用年度をグループ化して表示 | AW40: 降順
A41: 職種 | K41: 職種 | AW41: 昇順
A42: 雇用部課 | K42: 雇用部課 | AW42: 昇順
A43: 予算区分 | K43: 予算区分 | AW43: 昇順 | BI43: 一覧の並び順
A44: 業務コード | K44: 業務 | AW44: 昇順
A45: 予算コード | K45: 予算 | AW45: 昇順
A46: 配分先コード | K46: 配分先 | AW46: 昇順
A48: 画 面 補 足 説 明
B50: 〇個別単価について | AW50: ○入力項目
C51: 職種からユーザコードマスタ[UC0001]（職種マスタ）を参照し、個別単価設定可否フラグが1（可）の | AW51: 項目名 | BK51: 入力必須 | BP51: 桁数 | BS51: 入力制限等
C52: 場合、活性にて表示する。個別単価設定可否フラグが0（否）の場合、非活性にて表示する。 | AW52: 雇用情報ＩＤ | BK52: × | BP52: - | BS52: 新規作成：登録時に採番するので空白を表示 編集：登録されている雇用情報ＩＤを表示
C54: 活性 | AW54: 雇用年度 | BK54: 〇 | BP54: - | BS54: リストボックス ※新規作成の場合、システム日付より年度を設定
D55: 個別単価
AW56: 学生ID | BK56: 〇 | BP56: 11 | BS56: 半角数字
AW57: 学生氏名 | BK57: × | BP57: - | BS57: 表示項目
C58: 非活性 | AW58: 職種 | BK58: 〇 | BP58: - | BS58: リストボックス
D59: 個別単価 | AW59: 雇用部課 | BK59: 〇 | BP59: - | BS59: リストボックス
AW61: ●選択した職種によって科目コードから雇用終了日の制御が異なる
B62: 〇 | C62: 登録モード、編集モードの切替 | AW62: 職種：TA・SA
C63: 雇用情報マスタ画面の新規作成ボタンを押下し、雇用情報編集画面を表示した場合は、登録モードとする。 | AW63: 科目コード | BK63: 〇 | BP63: 8 | BS63: 半角数字
C64: 雇用情報マスタ画面の選択ボタンを押下し、雇用情報編集画面を表示した場合は、編集モードとする。 | AW64: クラスコード | BK64: 〇 | BP64: 3 | BS64: 半角数字
C65: 登録モード、編集モードではフッタ部のボタンの表示を変更する。 | AW65: 科目名 | BK65: × | BP65: - | BS65: 表示項目
AW66: 教員 | BK66: 〇 | BP66: - | BS66: 社員選択ポップアップより教員を選択
C67: 登録モード | BS67: ※科目を入力/選択時に主担当教員を設定
D68: （ガイダンス行） | AW68: 予算区分 | BK68: 〇 | BP68: - | BS68: リストボックス
AW69: 雇用開始日 | BK69: 〇 | BP69: - | BS69: 雇用年度と科目より学年暦マスタを参照し自動設定 ※1
AW70: 雇用終了日 | BK70: 〇 | BP70: - | BS70: 雇用年度と科目より学年暦マスタを参照し自動設定 ※1
D71: 登録 | AW71: ※1 科目情報（雇用年度（開講年度）、科目コード、クラスコード）から授業の開講期間を求め、
AW72: 学年暦の期間開始・終了日を使用する。学年暦種別については一律 1:標準 とする。
AX73: 例） | BB73: 2023年度 春学期開講科目 ⇒ 20230401～20230920
C74: 編集モード | BB74: 2023年度 秋学期開講科目 ⇒ 20230921～20240331
D75: （ガイダンス行） | BB75: 2023年度 通年開講科目 ⇒ 20230401～20240331
AW77: 職種：RA・留学生チューター・研究活動等支援員
D78: 更新 | J78: 削除 | AW78: 科目コード | BK78: × | BP78: - | BS78: 空白固定
AW79: クラスコード | BK79: × | BP79: - | BS79: 空白固定
AW80: 科目名 | BK80: × | BP80: - | BS80: 空白固定
AW81: 教員 | BK81: 〇 | BP81: - | BS81: 社員選択ポップアップより教員を選択
AW82: 予算区分 | BK82: 〇 | BP82: - | BS82: 固定値 ―（00）
AW83: 雇用開始日 | BK83: 〇 | BP83: - | BS83: 西暦日付
AW84: 雇用終了日 | BK84: 〇 | BP84: - | BS84: 西暦日付
A91: 画 面 補 足 説 明
B93: ○入力項目（続き） | AZ93: 〇複数身分IDの採番ルール
B94: 項目名 | P94: 入力必須 | U94: 桁数 | X94: 入力制限等 | BA94: 登録する各項目より複数身分IDを採番する
B95: 職種：LA
B96: 科目コード | P96: × | U96: - | X96: 空白固定 | BG96: 1 | BJ96: 0 | BM96: 1 | BP96: t | BS96: a | BV96: 0 | BY96: 0 | CB96: 1
B97: クラスコード | P97: × | U97: - | X97: 空白固定
B98: 科目名 | P98: × | U98: - | X98: 空白固定
B99: 教員 | P99: × | U99: - | X99: 空白固定
B100: 予算区分 | P100: 〇 | U100: - | X100: 固定値 ―（00） | BA100: 未使用 | BD100: 未使用 | BG100: 雇用部課コード | BP100: 職種コード | BV100: 学生 | BY100: 予算区分
B101: 雇用開始日 | P101: 〇 | U101: - | X101: 西暦日付
B102: 雇用終了日 | P102: 〇 | U102: - | X102: 西暦日付 | BA102: (１）雇用部課コード | BL102: ： | BN102: 学生雇用を募集した部課コードを表す。
B103: 職種：一般 | BN103: ※入力されている雇用部課をそのまま設定
B104: 科目コード | P104: × | U104: - | X104: 空白固定 | BA104: (２）職種コード | BL104: ： | BN104: 学生雇用を募集した職種コードを表す。
B105: クラスコード | P105: × | U105: - | X105: 空白固定 | BN105: ※ユーザコードマスタ[UC0001]（職種マスタ）より職種に
B106: 科目名 | P106: × | U106: - | X106: 空白固定 | BN106: 一致する名称3を設定
B107: 教員 | P107: × | U107: - | X107: 空白固定 | BA107: (３）学生所属コード | BL107: ： | BN107: 学生基本の学生所属コード・在学年次を表す。
B108: 予算区分 | P108: 〇 | U108: - | X108: リストボックス（51以降） | BN108: ※学生所属コードの先頭1桁目でコードマスタ[C00003]に
B109: 雇用開始日 | P109: 〇 | U109: - | X109: 西暦日付 | BN109: 一致するコード値名称1を設定
B110: 雇用終了日 | P110: 〇 | U110: - | X110: 西暦日付 | BA110: (４）予算区分コード | BL110: ： | BN110: 学生雇用の予算を表す。
B111: 業務コード | P111: △ | U111: - | X111: リストボックス | BN111: ※入力されている予算区分を設定
B112: 予算コード | P112: △ | U112: - | X112: リストボックス | BN112: ※職種が一般(学生アルバイト)の場合、以下の条件で予算区分コードを
B113: 配分先コード | P113: × | U113: - | X113: リストボックス | BO113: 重複チェックを行う。
B114: 個別単価 | P114: × | U114: 6 | X114: 半角数字 | BP114: 条件
B115: 業務内容等 | P115: △ | U115: 400 | BQ115: ・ | BR115: 同一雇用年度、学生(社員ID)、複数身分IDが設定されている
B116: 複数身分ＩＤ | P116: × | U116: - | X116: 新規作成：登録時に付与するので空白を表示 編集：登録されている複数身分ＩＤを表示 | BR116: かつ、同一業務コード、予算コード、配分先コードが
BR117: 登録されていて、予算区分が不一致の場合、エラーとする。
BQ118: ・ | BR118: 上記以外の場合
B119: ・ | C119: 業務コードと予算コードのどちらかが入力されていれば、業務コードと | BR119: 同一雇用年度、学生(社員ID)、複数身分IDが設定されていて
C120: 予算コードは必ず、双方の入力がないとエラーとする。 | BR120: 予算区分が一致する場合、エラーとする。
B122: ・ | C122: 業務内容等は職種が一般の場合は、必須項目とする。
B124: ●編集モードの場合、以下の項目を非活性とし、編集不可とする。 | AF124: 職種コード | BB124: 学生所属コード
B125: 項目名 | AG125: 職種コード | AM125: 職種 | AV125: 変換値 | BC125: 学生所属コード1桁目 | BM125: 課程名称 | CB125: 在学年次 | CH125: 変換値
B126: 雇用年度 | AG126: 01 | AM126: TA | AV126: ta | BC126: 1 | BM126: 学部 | CH126: 0
B127: 学生ID | AG127: 02 | AM127: SA | AV127: sa | BC127: 3 | BM127: 博士課程 前期課程・修士課程 | CH127: m
B128: 職種 | AG128: 03 | AM128: RA | AV128: ra | BC128: 4 | BM128: 博士課程 後期課程 | CH128: d
B129: 雇用部課 | AG129: 04 | AM129: LA | AV129: la | BC129: 5 | BM129: 博士課程 一貫制 | CB129: 2年次未満 | CH129: m
B130: 予算区分 | AG130: 05 | AM130: 留学生チューター | AV130: is | BC130: 5 | BM130: 博士課程 一貫制 | CB130: 3年次以上 | CH130: d
AG131: 06 | AM131: 研究活動等支援員 | AV131: rs | BC131: 6 | BM131: 専門職学位課程 | CH131: m
AG132: 51 | AM132: 一般 | AV132: pj | BC132: 9 | BM132: その他 | CH132: 0
A134: 画 面 補 足 説 明
B136: ○エラーメッセージ | AW136: ○職種が一般（学生アルバイト）の予算区分の重複チェック
C137: エラー条件 | X137: エラーメッセージ | AX137: ・ | AY137: 同一雇用年度、学生(社員ID)、複数身分IDが設定されている、かつ、同一業務コード、予算コード、
C138: 職種が51（一般）且つ、業務内容等が空の場合 | X138: 業務内容等を入力してください。 | AY138: 配分先コードが登録されていて、予算区分が不一致の場合、エラーとする。
...

Sheet 雇用情報マスタ取込
A1: システム名 | I1: =タイトル!I40 -> 学生勤務管理システム | AE1: 工 程 | AL1: 機能設計 | BI1: 作 成 | BM1: =タイトル!I46 -> 木田 優 | BW1: =タイトル!I47 -> 45196 | CF1: 管理記号 | CK1: =タイトル!I50 -> DUC010
A2: サブシステム名 | I2: 共通機能 | AE2: ドキュメント | AL2: =タイトル!I44 -> CZ-010_雇用情報マスタ | BI2: 改 訂 | BM2: 木田 優 | BW2: 45706
A4: 画面名称 | I4: =" " & RIGHT(CELL("filename",A1),LEN(CELL("filename",A1))-FIND("]",CELL("filename",A1))) -> 雇用情報マスタ取込 | AL4: 画面ＩＤ | AS4: CZ-010-04G | BI4: 利用想定ユーザー | BT4: 管理者、担当者
A5: 画面レイアウト | BI5: 機能概要
BJ7: ・ | BK7: 雇用情報マスタの一括登録又は一括更新を行う時に使用する。
BI12: 画面説明 （処理内容・アクション等）
BJ14: ・ | BK14: 取込ファイルはファイルを取込んだ後に取り込んだファイル名を表示する。
BJ16: ・ | BK16: 実行結果には入力されていた件数と取込に成功し登録した件数を表示する。
BJ18: ・ | BK18: アップロードボタンを押下すると、指定されたファイルを取り込む。
BK19: ※取り込む際にバリデーションチェックを行い、エラーがあれば
BL20: 取り込みを中止する。
BK21: ※管理者に限り、取込時のエラーチェックに特別対応が存在する
BL22: （画面補足説明の「管理者限定の特別対応について」参照）
A38: リストボックス | BI38: 権限による画面制御
A39: 項目名 | K39: 内容 | AW39: 並び順
BI43: 一覧の並び順
A48: 画 面 補 足 説 明
B50: ○雇用情報データフォーマット | AX50: 〇複数身分IDの採番ルール
C51: 項目名 | Q51: 入力必須 | V51: 備考 | AY51: 登録する各項目より複数身分IDを採番する
C52: 雇用情報通番 | Q52: 〇 | V52: 新規の時は空白、変更の時は雇用情報ダウンロード時に出力されている番号のまま
BE53: 1 | BH53: 0 | BK53: 1 | BN53: t | BQ53: a | BT53: 0 | BW53: 0 | BZ53: 1
C54: 雇用年度 | Q54: 〇
C55: 社員番号 | Q55: 〇 | V55: 学生ＩＤ
C56: 職種 | Q56: 〇 | V56: 01：ＴＡ、02：ＳＡ、03：ＲＡ、04：ＬＡ、05：留学生チューター、06：研究活動等支援員、51：一般
AY57: 未使用 | BB57: 未使用 | BE57: 雇用部課コード | BN57: 職種コード | BT57: 学生 | BW57: 予算区分
C58: 雇用部課コード | Q58: 〇 | V58: 101：法人事務室、102：監査室、103：募金課・・・・
C59: 予算区分 | Q59: 〇 | V59: 00：－、01：TA 学部、02：TA 大学院 ・・・・・ | AY59: (１）雇用部課コード | BJ59: ： | BL59: 学生雇用を募集した部課コードを表す。
C60: 科目コード | Q60: △ | BL60: ※入力されている雇用部課をそのまま設定
C61: クラスコード | Q61: △ | AY61: (２）職種コード | BJ61: ： | BL61: 学生雇用を募集した職種コードを表す。
C62: 科目名 | Q62: △ | BL62: ※ユーザコードマスタ[UC0001]（職種マスタ）より職種に
C63: 教員コード | Q63: △ | BL63: 一致する名称3を設定
C64: 雇用開始日 | Q64: 〇 | AY64: (３）学生所属コード | BJ64: ： | BL64: 学生基本の学生所属コード・在学年次を表す。
C65: 雇用終了日 | Q65: 〇 | BL65: ※学生所属コードの先頭1桁目でコードマスタ[C00003]に
C66: 業務コード | Q66: × | BL66: 一致するコード値名称1を設定
C67: 予算コード | Q67: × | AY67: (４）予算区分コード | BJ67: ： | BL67: 学生雇用の予算を表す。
C68: 配分先コード | Q68: × | BL68: ※入力されている予算区分を設定
C69: 業務内容等 | Q69: △ | BL69: ※職種が一般の場合、重複チェックあり
C70: 複数身分ＩＤ | Q70: - | V70: 新規の時は空白、変更の時は雇用情報ダウンロード時に出力されている番号のまま
AZ71: 職種コード
C72: 個別単価 | Q72: × | BA72: 職種コード | BG72: 職種 | BP72: 変換値
BA73: 01 | BG73: TA | BP73: ta
C74: ※個別単価について | BA74: 02 | BG74: SA | BP74: sa
D75: 個別単価は職種毎に設定の可否を設定しているので、給与単価テーブルより設定可否 | BA75: 03 | BG75: RA | BP75: ra
D76: フラグを参照し、設定否になっている職種に対して、個別単価が指定されている場合 | BA76: 04 | BG76: LA | BP76: la
D77: 取込みエラーとする。 | BA77: 05 | BG77: 留学生チューター | BP77: is
BA78: 06 | BG78: 研究活動等支援員 | BP78: rs
C79: ※教員コードについて | BA79: 51 | BG79: 一般 | BP79: pj
D80: ・ | E80: 設定されている教員コードが社員マスタの教員コードに存在しなければ、エラーとする
D81: ・ | E81: 教員コードが設定されていない且つ、科目コードが設定されている場合に科目の教員コードを | AZ81: 学生所属コード
E82: 自動的に設定する。 | BA82: 学生所属コード1桁目 | BK82: 課程名称 | BZ82: 在学年次 | CF82: 変換値
BA83: 1 | BK83: 学部 | CF83: 0
C84: ・ | D84: 業務コードと予算コードのどちらかが入力されていれば、業務コードと | BA84: 3 | BK84: 博士課程 前期課程・修士課程 | CF84: m
D85: 予算コードは必ず、双方の入力がないとエラーとする。 | BA85: 4 | BK85: 博士課程 後期課程 | CF85: d
BA86: 5 | BK86: 博士課程 一貫制 | BZ86: 2年次未満 | CF86: m
C87: ・ | D87: 必須：△の項目については職種によって必須かどうかが変わります。 | BA87: 5 | BK87: 博士課程 一貫制 | BZ87: 3年次以上 | CF87: d
D88: 条件については、雇用情報マスタ編集の補足説明参照。 | BA88: 6 | BK88: 専門職学位課程 | CF88: m
BA89: 9 | BK89: その他 | CF89: 0
A91: 画 面 補 足 説 明
B93: 〇 | C93: 雇用年度について
C94: 給与支給日マスタの雇用年度を参照し、雇用年度が未登録の場合には
C95: 取り込みエラーとする。
B97: 〇 | C97: 管理者限定の特別対応について
C98: ※業務・予算・配分先コードが入力されている場合のみ
C99: ★：業務マスタ・予算マスタ・配分先マスタの抽出キー
C100: ・ | D100: 担当者の場合、業務・予算・配分先コードは以下のマスタ全ての組み合わせが該当しなければ、エラーとする。
E102: 雇用情報データ | R102: 業務マスタ | AE102: 予算マスタ | AR102: 配分先マスタ
E103: 雇用部課コード★ | R103: 申請部署連番★ | AE103: 申請部署連番★ | AR103: 申請部署連番★
E105: 業務コード★ | R105: 業務連番 | AE105: 業務連番 | AR105: 配分先コード★
E107: 予算コード★ | R107: 業務コード★ | AE107: 予算コード★
E109: 配分先コード★
C113: ・ | D113: 管理者の場合、業務・予算・配分先コードは以下のマスタにそれぞれ存在しなければ、エラーとする。
D114: また、予算マスタと配分先マスタは業務マスタと組み合わせが該当しなければ、エラーとする。
E116: 雇用情報データ | R116: 業務マスタ | AE116: 予算マスタ | AR116: 配分先マスタ
E117: 雇用部課コード | R117: 申請部署連番 | AE117: 申請部署連番 | AR117: 申請部署連番
E119: 業務コード★ | R119: 業務連番 | AE119: 業務連番 | AR119: 配分先コード★
E121: 予算コード★ | R121: 業務コード★ | AE121: 予算コード★
E123: 配分先コード★
